task_4/f1_fsm.sv
module f1_fsm (
    input logic clk,
    input logic rst,
    input logic en,
    input logic trigger,
    output logic [7:0] lights,
    output logic cmd_seq,
    output logic cmd_delay
);



// Define the states 
typedef enum {S_1, S_2, S_3, S_4, S_5, S_6, S_7, S_8, S_0} my_state;
my_state current_state = S_0, next_state;

always_ff @(posedge clk)
    if (rst) current_state <= S_0;
    else     current_state <= next_state;


always_comb begin
    if (trigger && !cmd_delay) begin 
        cmd_seq = 1;
    end 
    
    if (en) begin
        case (current_state)
        S_0:             next_state = S_1;
        S_1:             next_state = S_2;
        S_2:             next_state = S_3;
        S_3:             next_state = S_4;
        S_4:             next_state = S_5;
        S_5:             next_state = S_6;
        S_6:             next_state = S_7;
        S_7:             next_state = S_8;
        S_8:             next_state = S_0;
        default:         next_state = S_0;
        endcase

        case (current_state)
        S_0: 
        begin 
            lights = 8'b0;
            cmd_seq = 0;
            cmd_delay = 0;
        end 
        S_1:
        begin
            lights = 8'b1;
            cmd_seq = 1;
            cmd_delay = 0;
        end 
        S_2: lights = 8'b11;
        S_3: lights = 8'b111;
        S_4: lights = 8'b1111;
        S_5: lights = 8'b11111;
        S_6: lights = 8'b111111;
        S_7: lights = 8'b1111111;
        S_8:
        begin 
            lights = 8'b11111111;
            cmd_seq = 0;
            cmd_delay = 1;
        end 
        default: lights = 8'b0;
    endcase 
    end
end

    
endmodule

















// // Next state logic 
// always_comb 
//     if (trigger && !cmd_delay) cmd_seq = 1;
//     if (en) begin
//     case (current_state)
//         S_0: if  next_state = S_1;
//         
//         S_1:                next_state = S_2;
//         
//         S_2:                next_state = S_3;
//         
//         S_3:                next_state = S_4;
//         
//         S_4:                next_state = S_5;
//         
//         S_5:                next_state = S_6;
//         
//         S_6:                next_state = S_7;
//         
//         S_7:                next_state = S_8;
//         
//         S_8:                next_state = S_0;
//         
//         default: next_state = S_0;
//     endcase 

// // State transition
// always_ff @(posedge clk) begin
//     if (rst)    current_state <= S_0;
//     else        current_state <= next_state;
// end

// // Output logic 

// always_comb
//     case (current_state)
//         S_0:    lights = 8'b0;
//         S_1:    lights = 8'b1;
//                 cmd_seq = 1;
//         S_2:    lights = 8'b11;
//                 cmd_seq = 1;
//         S_3:    lights = 8'b111;
//                 cmd_seq = 1;
//         S_4:    lights = 8'b1111;
//                 cmd_seq = 1;
//         S_5:    lights = 8'b11111;
//                 cmd_seq = 1;
//         S_6:    lights = 8'b111111;
//                 cmd_seq = 1;
//         S_7:    lights = 8'b1111111;
//                 cmd_seq = 1;
//         S_8:    lights = 8'b11111111;
//                 cmd_seq = 0;
//                 cmd_delay = 1;
//     endcase

// endmodule

task_4/clktick.sv
module clktick #(
	parameter WIDTH = 16
)(
  // interface signals
  input  logic             clk,      // clock 
  input  logic             rst,      // reset
  input  logic             en,       // enable signal
  input  logic [WIDTH-1:0] N,     	 // clock divided by N+1
  output logic  		       tick      // tick output
);

logic [WIDTH-1:0] count;

always_ff @ (posedge clk)
    if (rst) begin
        tick <= 1'b0;
        count <= N;  
        end
    else if (en) begin
	    if (count == 0) begin
		    tick <= 1'b1;
		    count <= N;
	        end
	    else begin
		    tick <= 1'b0;
		    count <= count - 1'b1;
	        end
        end
endmodule

task_4/delay.sv
module delay #(
	parameter WIDTH = 7    // no of bits in delay counter
)(
    input   logic               clk,        // clock signal
    input   logic               rst,        // reset signal
    input   logic               trigger_delay,    // trigger_delay input signal
    input   logic [WIDTH-1:0]   n,          // no of clock cycle delay
    output  logic               time_out    // output pulse signal
);
    // Declare counter
    logic [WIDTH-1:0]   count = {WIDTH{1'b0}};            // internal counter

    // Define our states
    typedef enum {IDLE, COUNTING, TIME_OUT, WAIT_LOW}  my_state;
    my_state current_state, next_state;

    // counter
    always_ff @(posedge clk)
        if (rst | trigger_delay | count=={WIDTH{1'b0}}) count <= n - 1'b1;
        else                                count <= count - 1'b1;

    // state transition
    always_ff @(posedge clk)
        if (rst)    current_state <= IDLE;
        else        current_state <= next_state; 

    // next state logic
    always_comb
        case (current_state)
            IDLE:       if (trigger_delay==1'b1)  next_state = COUNTING;
                        else    next_state = current_state;
            COUNTING:   if (count=={WIDTH{1'b0}}) next_state = TIME_OUT;
                        else    next_state = current_state;
            TIME_OUT:   if (trigger_delay==1'b1)  next_state = WAIT_LOW;
                        else    next_state = IDLE;
            WAIT_LOW:   if (trigger_delay==1'b0)  next_state = IDLE;
                        else    next_state = current_state;
            default: next_state = IDLE;
        endcase
    
    // output logic
    always_comb
        case (current_state)
            IDLE:       time_out = 1'b0;
            COUNTING:   time_out = 1'b0;
            TIME_OUT:   time_out = 1'b1;
            WAIT_LOW:   time_out = 1'b0;
            default:    time_out = 1'b0;
        endcase
endmodule

task_4/lfsr_7.sv
module lfsr_7 (
    input logic         clk,
    input logic         rst,
    input logic         en,
    output logic [6:0]  data_out
);

logic [7:1] sreg; 

always_ff @(posedge clk, posedge rst) begin
    if (rst)
        sreg <= 7'b1; 
    else if(en)
        sreg <= {sreg[6:1], sreg[3] ^ sreg[7]};
    else 
        sreg <= sreg;
end

assign data_out = sreg;
endmodule

task_4/starting_light.sv
module starting_light  (
    input logic clk,
    input logic rst,
    input logic trigger, 
    output logic [7:0] lights
);


logic tick;
logic time_out;
logic [6:0] data_out;
/* verilator lint_off UNOPTFLAT */
logic cmd_delay;
logic cmd_seq;



lfsr_7 lfsr7 (
    .clk (clk),
    .en (1),
    .rst (rst),
    .data_out (data_out)
);

delay delayer (
    .clk (clk),
    .rst (rst),
    .trigger_delay(cmd_delay),
    .n (data_out),
    .time_out (time_out)

);

clktick one_second (
    .N (46),
    .en (cmd_seq),
    .rst (rst),
    .clk (clk),
    .tick (tick)
);

f1_fsm F1 (
    .clk (clk),
    .trigger (trigger),
    .en (cmd_seq ? tick : time_out),
    .rst (rst),
    .cmd_delay (cmd_delay),
    .cmd_seq (cmd_seq),
    .lights (lights)
);

endmodule

task_4/starting_light.vcd
$version Generated by VerilatedVcd $end
$date Wed Nov 16 16:16:21 2022 $end
$timescale 1ps $end

 $scope module TOP $end
  $var wire  1 - clk $end
  $var wire  8 0 lights [7:0] $end
  $var wire  1 . rst $end
  $var wire  1 / trigger $end
  $scope module starting_light $end
   $var wire  1 - clk $end
   $var wire  1 ) cmd_delay $end
   $var wire  1 * cmd_seq $end
   $var wire  7 1 data_out [6:0] $end
   $var wire  8 0 lights [7:0] $end
   $var wire  1 . rst $end
   $var wire  1 # tick $end
   $var wire  1 $ time_out $end
   $var wire  1 / trigger $end
   $scope module F1 $end
    $var wire  1 - clk $end
    $var wire  1 ) cmd_delay $end
    $var wire  1 * cmd_seq $end
    $var wire 32 % current_state [31:0] $end
    $var wire  1 + en $end
    $var wire  8 0 lights [7:0] $end
    $var wire 32 , next_state [31:0] $end
    $var wire  1 . rst $end
    $var wire  1 / trigger $end
   $upscope $end
   $scope module delayer $end
    $var wire 32 3 WIDTH [31:0] $end
    $var wire  1 - clk $end
    $var wire  7 & count [6:0] $end
    $var wire 32 ' current_state [31:0] $end
    $var wire  7 1 n [6:0] $end
    $var wire 32 2 next_state [31:0] $end
    $var wire  1 . rst $end
    $var wire  1 $ time_out $end
    $var wire  1 ) trigger_delay $end
   $upscope $end
   $scope module lfsr7 $end
    $var wire  1 - clk $end
    $var wire  7 1 data_out [6:0] $end
    $var wire  1 4 en $end
    $var wire  1 . rst $end
    $var wire  7 1 sreg [7:1] $end
   $upscope $end
   $scope module one_second $end
    $var wire 16 6 N [15:0] $end
    $var wire 32 5 WIDTH [31:0] $end
    $var wire  1 - clk $end
    $var wire 16 ( count [15:0] $end
    $var wire  1 * en $end
    $var wire  1 . rst $end
    $var wire  1 # tick $end
   $upscope $end
  $upscope $end
 $upscope $end
$enddefinitions $end


#0
0#
0$
b00000000000000000000000000000000 %
b0000000 &
b00000000000000000000000000000000 '
b0000000000000000 (
0)
0*
0+
b00000000000000000000000000000000 ,
1-
0.
0/
b00000000 0
b0000000 1
b00000000000000000000000000000000 2
b00000000000000000000000000000111 3
14
b00000000000000000000000000010000 5
b0000000000101110 6
#1
b00000000000000000000000000001000 %
0-
#2
b00000000000000000000000000000000 %
b1111111 &
1-
1.
#3
0-
b0000001 1
#4
b00000000000000000000000000001000 %
b0000000 &
b0000000000101110 (
1-
#5
0-
#6
1-
0.
#7
0-
#8
b00000000000000000000000000000000 %
1-
b0000010 1
#9
0-
#10
b0000001 &
1-
b0000100 1
#11
0-
#12
b0000000 &
1-
b0001001 1
#13
0-
#14
b0001000 &
1-
b0010010 1
#15
0-
#16
b0000111 &
1-
b0100100 1
#17
0-
#18
b0000110 &
1-
b1001001 1
#19
0-
#20
b0000101 &
1-
b0010011 1
#21
0-
#22
b0000100 &
1-
b0100110 1
#23
0-
#24
b0000011 &
1-
b1001101 1
#25
0-
#26
b0000010 &
1-
b0011010 1
#27
0-
#28
b0000001 &
1-
b0110100 1
#29
0-
#30
b0000000 &
1-
b1101001 1
#31
0-
#32
b1101000 &
1-
b1010011 1
#33
0-
#34
b1100111 &
1-
b0100111 1
#35
0-
#36
b1100110 &
1-
b1001111 1
#37
0-
#38
b1100101 &
1-
b0011110 1
#39
0-
#40
b1100100 &
1-
b0111101 1
#41
0-
#42
b1100011 &
1-
b1111011 1
#43
0-
#44
b1100010 &
1-
b1110111 1
#45
0-
#46
b1100001 &
1-
b1101110 1
#47
0-
#48
b1100000 &
1-
b1011100 1
#49
0-
#50
b1011111 &
1-
b0111000 1
#51
0-
#52
b1011110 &
1-
b1110000 1
#53
0-
#54
b1011101 &
1-
b1100001 1
#55
0-
#56
b1011100 &
1-
b1000011 1
#57
0-
#58
b1011011 &
1-
b0000111 1
#59
0-
#60
b1011010 &
1-
b0001111 1
#61
0-
#62
b1011001 &
1-
b0011111 1
#63
0-
#64
b1011000 &
1-
b0111111 1
#65
0-
#66
b1010111 &
1-
b1111111 1
#67
0-
#68
b1010110 &
1-
b1111110 1
#69
0-
#70
b1010101 &
1-
b1111100 1
#71
0-
#72
b1010100 &
1-
b1111000 1
#73
0-
#74
b1010011 &
1-
b1110001 1
#75
0-
#76
b1010010 &
1-
b1100011 1
#77
0-
#78
b1010001 &
1-
b1000111 1
#79
0-
#80
b1010000 &
1-
b0001110 1
#81
0-
#82
b1001111 &
1-
b0011101 1
#83
0-
#84
b1001110 &
1-
b0111011 1
#85
0-
#86
b1001101 &
1-
b1110110 1
#87
0-
#88
b1001100 &
1-
b1101100 1
#89
0-
#90
b1001011 &
1-
b1011000 1
#91
0-
#92
b1001010 &
1-
b0110001 1
#93
0-
#94
b1001001 &
1-
b1100010 1
#95
0-
#96
b1001000 &
1-
b1000101 1
#97
0-
#98
b1000111 &
1-
b0001010 1
#99
0-
#100
b1000110 &
1-
b0010100 1
#101
0-
#102
b1000101 &
1-
b0101001 1
#103
0-
#104
b1000100 &
1-
b1010010 1
#105
0-
#106
b1000011 &
1-
b0100101 1
#107
0-
#108
b1000010 &
1-
b1001011 1
#109
0-
#110
b1000001 &
1-
b0010111 1
#111
0-
#112
b1000000 &
1-
b0101111 1
#113
0-
#114
b0111111 &
1-
b1011111 1
#115
0-
#116
b0111110 &
1-
b0111110 1
#117
0-
#118
b0111101 &
1-
b1111101 1
#119
0-
#120
b0111100 &
1-
b1111010 1
#121
0-
#122
b0111011 &
1-
b1110101 1
#123
0-
#124
b0111010 &
1-
b1101010 1
#125
0-
#126
b0111001 &
1-
b1010101 1
#127
0-
#128
b0111000 &
1-
b0101010 1
#129
0-
#130
b0110111 &
1-
b1010100 1
#131
0-
#132
b0110110 &
1-
b0101000 1
#133
0-
#134
b0110101 &
1-
b1010000 1
#135
0-
#136
b0110100 &
1-
b0100001 1
#137
0-
#138
b0110011 &
1-
b1000010 1
#139
0-
#140
b0110010 &
1-
b0000101 1
#141
0-
#142
b0110001 &
1-
b0001011 1
#143
0-
#144
b0110000 &
1-
b0010110 1
#145
0-
#146
b0101111 &
1-
b0101101 1
#147
0-
#148
b0101110 &
1-
b1011011 1
#149
0-
#150
b0101101 &
1-
b0110111 1
#151
0-
#152
b0101100 &
1-
b1101111 1
#153
0-
#154
b0101011 &
1-
b1011110 1
#155
0-
#156
b0101010 &
1-
b0111100 1
#157
0-
#158
b0101001 &
1-
b1111001 1
#159
0-
#160
b0101000 &
1-
b1110011 1
#161
0-
#162
b0100111 &
1-
b1100111 1
#163
0-
#164
b0100110 &
1-
b1001110 1
#165
0-
#166
b0100101 &
1-
b0011100 1
#167
0-
#168
b0100100 &
1-
b0111001 1
#169
0-
#170
b0100011 &
1-
b1110010 1
#171
0-
#172
b0100010 &
1-
b1100101 1
#173
0-
#174
b0100001 &
1-
b1001010 1
#175
0-
#176
b0100000 &
1-
b0010101 1
#177
0-
#178
b0011111 &
1-
b0101011 1
#179
0-
#180
b0011110 &
1-
b1010110 1
#181
0-
#182
b0011101 &
1-
b0101100 1
#183
0-
#184
b0011100 &
1-
b1011001 1
#185
0-
#186
b0011011 &
1-
b0110011 1
#187
0-
#188
b0011010 &
1-
b1100110 1
#189
0-
#190
b0011001 &
1-
b1001100 1
#191
0-
#192
b0011000 &
1-
b0011000 1
#193
0-
#194
b0010111 &
1-
b0110000 1
#195
0-
#196
b0010110 &
1-
b1100000 1
#197
0-
#198
b0010101 &
1-
b1000001 1
#199
0-
#200
b0010100 &
1-
b0000011 1
#201
0-
#202
b0010011 &
1-
b0000110 1
#203
0-
#204
b0010010 &
1-
b0001101 1
#205
0-
#206
b0010001 &
1-
b0011011 1
#207
0-
#208
b0010000 &
1-
b0110110 1
#209
0-
#210
b0001111 &
1-
b1101101 1
#211
0-
#212
b0001110 &
1-
b1011010 1
#213
0-
#214
b0001101 &
1-
b0110101 1
#215
0-
#216
b0001100 &
1-
b1101011 1
#217
0-
#218
b0001011 &
1-
b1010111 1
#219
0-
#220
b0001010 &
1-
b0101110 1
#221
0-
#222
b0001001 &
1-
b1011101 1
#223
0-
#224
b0001000 &
1-
b0111010 1
#225
0-
#226
b0000111 &
1-
b1110100 1
#227
0-
#228
b0000110 &
1-
b1101000 1
#229
0-
#230
b0000101 &
1-
b1010001 1
#231
0-
#232
b0000100 &
1-
b0100011 1
#233
0-
#234
b0000011 &
1-
b1000110 1
#235
0-
#236
b0000010 &
1-
b0001100 1
#237
0-
#238
b0000001 &
1-
b0011001 1
#239
0-
#240
b0000000 &
1-
b0110010 1
#241
0-
#242
b0110001 &
1-
b1100100 1
#243
0-
#244
b0110000 &
1-
b1001000 1
#245
0-
#246
b0101111 &
1-
b0010001 1
#247
0-
#248
b0101110 &
1-
b0100010 1
#249
0-
#250
b0101101 &
1-
b1000100 1
#251
0-
#252
b0101100 &
1-
b0001000 1
#253
0-
#254
b0101011 &
1-
b0010000 1
#255
0-
#256
b0101010 &
1-
b0100000 1
#257
0-
#258
b0101001 &
1-
b1000000 1
#259
0-
#260
b0101000 &
1-
b0000001 1
#261
0-
#262
b0100111 &
1-
b0000010 1
#263
0-
#264
b0100110 &
1-
b0000100 1
#265
0-
#266
b0100101 &
1-
b0001001 1
#267
0-
#268
b0100100 &
1-
b0010010 1
#269
0-
#270
b0100011 &
1-
b0100100 1
#271
0-
#272
b0100010 &
1-
b1001001 1
#273
0-
#274
b0100001 &
1-
b0010011 1
#275
0-
#276
b0100000 &
1-
b0100110 1
#277
0-
#278
b0011111 &
1-
b1001101 1
#279
0-
#280
b0011110 &
1-
b0011010 1
#281
0-
#282
b0011101 &
1-
b0110100 1
#283
0-
#284
b0011100 &
1-
b1101001 1
#285
0-
#286
b0011011 &
1-
b1010011 1
#287
0-
#288
b0011010 &
1-
b0100111 1
#289
0-
#290
b0011001 &
1-
b1001111 1
#291
0-
#292
b0011000 &
1-
b0011110 1
#293
0-
#294
b0010111 &
1-
b0111101 1
#295
0-
#296
b0010110 &
1-
b1111011 1
#297
0-
#298
b0010101 &
1-
b1110111 1
#299
0-
#300
b0010100 &
1-
b1101110 1
#301
0-
#302
b0010011 &
1-
b1011100 1
#303
0-
#304
b0010010 &
1-
b0111000 1
#305
0-
#306
b0010001 &
1-
b1110000 1
#307
0-
#308
b0010000 &
1-
b1100001 1
#309
0-
#310
b0001111 &
1-
b1000011 1
#311
0-
#312
b0001110 &
1-
b0000111 1
#313
0-
#314
b0001101 &
1-
b0001111 1
#315
0-
#316
b0001100 &
1-
b0011111 1
#317
0-
#318
b0001011 &
1-
b0111111 1
#319
0-
#320
b0001010 &
1-
b1111111 1
#321
0-
#322
b0001001 &
1-
b1111110 1
#323
0-
#324
b0001000 &
1-
b1111100 1
#325
0-
#326
b0000111 &
1-
b1111000 1
#327
0-
#328
b0000110 &
1-
b1110001 1
#329
0-
#330
b0000101 &
1-
b1100011 1
#331
0-
#332
b0000100 &
1-
b1000111 1
#333
0-
#334
b0000011 &
1-
b0001110 1
#335
0-
#336
b0000010 &
1-
b0011101 1
#337
0-
#338
b0000001 &
1-
b0111011 1
#339
0-
#340
b0000000 &
1-
1/
b1110110 1
#341
1*
0-
#342
b1110101 &
b0000000000101101 (
1-
0/
b1101100 1
#343
0-
#344
b1110100 &
b0000000000101100 (
1-
b1011000 1
#345
0-
#346
b1110011 &
b0000000000101011 (
1-
b0110001 1
#347
0-
#348
b1110010 &
b0000000000101010 (
1-
b1100010 1
#349
0-
#350
b1110001 &
b0000000000101001 (
1-
b1000101 1
#351
0-
#352
b1110000 &
b0000000000101000 (
1-
b0001010 1
#353
0-
#354
b1101111 &
b0000000000100111 (
1-
b0010100 1
#355
0-
#356
b1101110 &
b0000000000100110 (
1-
b0101001 1
#357
0-
#358
b1101101 &
b0000000000100101 (
1-
b1010010 1
#359
0-
#360
b1101100 &
b0000000000100100 (
1-
b0100101 1
#361
0-
#362
b1101011 &
b0000000000100011 (
1-
b1001011 1
#363
0-
#364
b1101010 &
b0000000000100010 (
1-
b0010111 1
#365
0-
#366
b1101001 &
b0000000000100001 (
1-
b0101111 1
#367
0-
#368
b1101000 &
b0000000000100000 (
1-
b1011111 1
#369
0-
#370
b1100111 &
b0000000000011111 (
1-
b0111110 1
#371
0-
#372
b1100110 &
b0000000000011110 (
1-
b1111101 1
#373
0-
#374
b1100101 &
b0000000000011101 (
1-
b1111010 1
#375
0-
#376
b1100100 &
b0000000000011100 (
1-
b1110101 1
#377
0-
#378
b1100011 &
b0000000000011011 (
1-
b1101010 1
#379
0-
#380
b1100010 &
b0000000000011010 (
1-
b1010101 1
#381
0-
#382
b1100001 &
b0000000000011001 (
1-
b0101010 1
#383
0-
#384
b1100000 &
b0000000000011000 (
1-
b1010100 1
#385
0-
#386
b1011111 &
b0000000000010111 (
1-
b0101000 1
#387
0-
#388
b1011110 &
b0000000000010110 (
1-
b1010000 1
#389
0-
#390
b1011101 &
b0000000000010101 (
1-
b0100001 1
#391
0-
#392
b1011100 &
b0000000000010100 (
1-
b1000010 1
#393
0-
#394
b1011011 &
b0000000000010011 (
1-
b0000101 1
#395
0-
#396
b1011010 &
b0000000000010010 (
1-
b0001011 1
#397
0-
#398
b1011001 &
b0000000000010001 (
1-
b0010110 1
#399
0-
#400
b1011000 &
b0000000000010000 (
1-
b0101101 1
#401
0-
#402
b1010111 &
b0000000000001111 (
1-
b1011011 1
#403
0-
#404
b1010110 &
b0000000000001110 (
1-
b0110111 1
#405
0-
#406
b1010101 &
b0000000000001101 (
1-
b1101111 1
#407
0-
#408
b1010100 &
b0000000000001100 (
1-
b1011110 1
#409
0-
#410
b1010011 &
b0000000000001011 (
1-
b0111100 1
#411
0-
#412
b1010010 &
b0000000000001010 (
1-
b1111001 1
#413
0-
#414
b1010001 &
b0000000000001001 (
1-
b1110011 1
#415
0-
#416
b1010000 &
b0000000000001000 (
1-
b1100111 1
#417
0-
#418
b1001111 &
b0000000000000111 (
1-
b1001110 1
#419
0-
#420
b1001110 &
b0000000000000110 (
1-
b0011100 1
#421
0-
#422
b1001101 &
b0000000000000101 (
1-
b0111001 1
#423
0-
#424
b1001100 &
b0000000000000100 (
1-
b1110010 1
#425
0-
#426
b1001011 &
b0000000000000011 (
1-
b1100101 1
#427
0-
#428
b1001010 &
b0000000000000010 (
1-
b1001010 1
#429
0-
#430
b1001001 &
b0000000000000001 (
1-
b0010101 1
#431
0-
#432
b1001000 &
b0000000000000000 (
1-
b0101011 1
#433
0-
#434
1#
b1000111 &
b0000000000101110 (
1+
b00000000000000000000000000000001 ,
1-
b00000001 0
b1010110 1
#435
0-
#436
0#
b00000000000000000000000000000001 %
b1000110 &
b0000000000101101 (
0+
1-
b0101100 1
#437
0-
#438
b1000101 &
b0000000000101100 (
1-
b1011001 1
#439
0-
#440
b1000100 &
b0000000000101011 (
1-
b0110011 1
#441
0-
#442
b1000011 &
b0000000000101010 (
1-
b1100110 1
#443
0-
#444
b1000010 &
b0000000000101001 (
1-
b1001100 1
#445
0-
#446
b1000001 &
b0000000000101000 (
1-
b0011000 1
#447
0-
#448
b1000000 &
b0000000000100111 (
1-
b0110000 1
#449
0-
#450
b0111111 &
b0000000000100110 (
1-
b1100000 1
#451
0-
#452
b0111110 &
b0000000000100101 (
1-
b1000001 1
#453
0-
#454
b0111101 &
b0000000000100100 (
1-
b0000011 1
#455
0-
#456
b0111100 &
b0000000000100011 (
1-
b0000110 1
#457
0-
#458
b0111011 &
b0000000000100010 (
1-
b0001101 1
#459
0-
#460
b0111010 &
b0000000000100001 (
1-
b0011011 1
#461
0-
#462
b0111001 &
b0000000000100000 (
1-
b0110110 1
#463
0-
#464
b0111000 &
b0000000000011111 (
1-
b1101101 1
#465
0-
#466
b0110111 &
b0000000000011110 (
1-
b1011010 1
#467
0-
#468
b0110110 &
b0000000000011101 (
1-
b0110101 1
#469
0-
#470
b0110101 &
b0000000000011100 (
1-
b1101011 1
#471
0-
#472
b0110100 &
b0000000000011011 (
1-
b1010111 1
#473
0-
#474
b0110011 &
b0000000000011010 (
1-
b0101110 1
#475
0-
#476
b0110010 &
b0000000000011001 (
1-
b1011101 1
#477
0-
#478
b0110001 &
b0000000000011000 (
1-
b0111010 1
#479
0-
#480
b0110000 &
b0000000000010111 (
1-
b1110100 1
#481
0-
#482
b0101111 &
b0000000000010110 (
1-
b1101000 1
#483
0-
#484
b0101110 &
b0000000000010101 (
1-
b1010001 1
#485
0-
#486
b0101101 &
b0000000000010100 (
1-
b0100011 1
#487
0-
#488
b0101100 &
b0000000000010011 (
1-
b1000110 1
#489
0-
#490
b0101011 &
b0000000000010010 (
1-
b0001100 1
#491
0-
#492
b0101010 &
b0000000000010001 (
1-
b0011001 1
#493
0-
#494
b0101001 &
b0000000000010000 (
1-
b0110010 1
#495
0-
#496
b0101000 &
b0000000000001111 (
1-
b1100100 1
#497
0-
#498
b0100111 &
b0000000000001110 (
1-
b1001000 1
#499
0-
#500
b0100110 &
b0000000000001101 (
1-
b0010001 1
#501
0-
#502
b0100101 &
b0000000000001100 (
1-
b0100010 1
#503
0-
#504
b0100100 &
b0000000000001011 (
1-
b1000100 1
#505
0-
#506
b0100011 &
b0000000000001010 (
1-
b0001000 1
#507
0-
#508
b0100010 &
b0000000000001001 (
1-
b0010000 1
#509
0-
#510
b0100001 &
b0000000000001000 (
1-
b0100000 1
#511
0-
#512
b0100000 &
b0000000000000111 (
1-
b1000000 1
#513
0-
#514
b0011111 &
b0000000000000110 (
1-
b0000001 1
#515
0-
#516
b0011110 &
b0000000000000101 (
1-
b0000010 1
#517
0-
#518
b0011101 &
b0000000000000100 (
1-
b0000100 1
#519
0-
#520
b0011100 &
b0000000000000011 (
1-
b0001001 1
#521
0-
#522
b0011011 &
b0000000000000010 (
1-
b0010010 1
#523
0-
#524
b0011010 &
b0000000000000001 (
1-
b0100100 1
#525
0-
#526
b0011001 &
b0000000000000000 (
1-
b1001001 1
#527
0-
#528
1#
b0011000 &
b0000000000101110 (
1+
b00000000000000000000000000000010 ,
1-
b00000011 0
b0010011 1
#529
0-
#530
0#
b00000000000000000000000000000010 %
b0010111 &
b0000000000101101 (
0+
1-
b0100110 1
#531
0-
#532
b0010110 &
b0000000000101100 (
1-
b1001101 1
#533
0-
#534
b0010101 &
b0000000000101011 (
1-
b0011010 1
#535
0-
#536
b0010100 &
b0000000000101010 (
1-
b0110100 1
#537
0-
#538
b0010011 &
b0000000000101001 (
1-
b1101001 1
#539
0-
#540
b0010010 &
b0000000000101000 (
1-
b1010011 1
#541
0-
#542
b0010001 &
b0000000000100111 (
1-
b0100111 1
#543
0-
#544
b0010000 &
b0000000000100110 (
1-
b1001111 1
#545
0-
#546
b0001111 &
b0000000000100101 (
1-
b0011110 1
#547
0-
#548
b0001110 &
b0000000000100100 (
1-
b0111101 1
#549
0-
#550
b0001101 &
b0000000000100011 (
1-
b1111011 1
#551
0-
#552
b0001100 &
b0000000000100010 (
1-
b1110111 1
#553
0-
#554
b0001011 &
b0000000000100001 (
1-
b1101110 1
#555
0-
#556
b0001010 &
b0000000000100000 (
1-
b1011100 1
#557
0-
#558
b0001001 &
b0000000000011111 (
1-
b0111000 1
#559
0-
#560
b0001000 &
b0000000000011110 (
1-
b1110000 1
#561
0-
#562
b0000111 &
b0000000000011101 (
1-
b1100001 1
#563
0-
#564
b0000110 &
b0000000000011100 (
1-
b1000011 1
#565
0-
#566
b0000101 &
b0000000000011011 (
1-
b0000111 1
#567
0-
#568
b0000100 &
b0000000000011010 (
1-
b0001111 1
#569
0-
#570
b0000011 &
b0000000000011001 (
1-
b0011111 1
#571
0-
#572
b0000010 &
b0000000000011000 (
1-
b0111111 1
#573
0-
#574
b0000001 &
b0000000000010111 (
1-
b1111111 1
#575
0-
#576
b0000000 &
b0000000000010110 (
1-
b1111110 1
#577
0-
#578
b1111101 &
b0000000000010101 (
1-
b1111100 1
#579
0-
#580
b1111100 &
b0000000000010100 (
1-
b1111000 1
#581
0-
#582
b1111011 &
b0000000000010011 (
1-
b1110001 1
#583
0-
#584
b1111010 &
b0000000000010010 (
1-
b1100011 1
#585
0-
#586
b1111001 &
b0000000000010001 (
1-
b1000111 1
#587
0-
#588
b1111000 &
b0000000000010000 (
1-
b0001110 1
#589
0-
#590
b1110111 &
b0000000000001111 (
1-
b0011101 1
#591
0-
#592
b1110110 &
b0000000000001110 (
1-
b0111011 1
#593
0-
#594
b1110101 &
b0000000000001101 (
1-
b1110110 1
#595
0-
#596
b1110100 &
b0000000000001100 (
1-
b1101100 1
#597
0-
#598
b1110011 &
b0000000000001011 (
1-
b1011000 1
#599
0-
#600
b1110010 &
b0000000000001010 (
1-
b0110001 1
#601
0-
#602
b1110001 &
b0000000000001001 (
1-
b1100010 1
#603
0-
#604
b1110000 &
b0000000000001000 (
1-
b1000101 1
#605
0-
#606
b1101111 &
b0000000000000111 (
1-
b0001010 1
#607
0-
#608
b1101110 &
b0000000000000110 (
1-
b0010100 1
#609
0-
#610
b1101101 &
b0000000000000101 (
1-
b0101001 1
#611
0-
#612
b1101100 &
b0000000000000100 (
1-
b1010010 1
#613
0-
#614
b1101011 &
b0000000000000011 (
1-
b0100101 1
#615
0-
#616
b1101010 &
b0000000000000010 (
1-
b1001011 1
#617
0-
#618
b1101001 &
b0000000000000001 (
1-
b0010111 1
#619
0-
#620
b1101000 &
b0000000000000000 (
1-
b0101111 1
#621
0-
#622
1#
b1100111 &
b0000000000101110 (
1+
b00000000000000000000000000000011 ,
1-
b00000111 0
b1011111 1
#623
0-
#624
0#
b00000000000000000000000000000011 %
b1100110 &
b0000000000101101 (
0+
1-
b0111110 1
#625
0-
#626
b1100101 &
b0000000000101100 (
1-
b1111101 1
#627
0-
#628
b1100100 &
b0000000000101011 (
1-
b1111010 1
#629
0-
#630
b1100011 &
b0000000000101010 (
1-
b1110101 1
#631
0-
#632
b1100010 &
b0000000000101001 (
1-
b1101010 1
#633
0-
#634
b1100001 &
b0000000000101000 (
1-
b1010101 1
#635
0-
#636
b1100000 &
b0000000000100111 (
1-
b0101010 1
#637
0-
#638
b1011111 &
b0000000000100110 (
1-
b1010100 1
#639
0-
#640
b1011110 &
b0000000000100101 (
1-
b0101000 1
#641
0-
#642
b1011101 &
b0000000000100100 (
1-
b1010000 1
#643
0-
#644
b1011100 &
b0000000000100011 (
1-
b0100001 1
#645
0-
#646
b1011011 &
b0000000000100010 (
1-
b1000010 1
#647
0-
#648
b1011010 &
b0000000000100001 (
1-
b0000101 1
#649
0-
#650
b1011001 &
b0000000000100000 (
1-
b0001011 1
#651
0-
#652
b1011000 &
b0000000000011111 (
1-
b0010110 1
#653
0-
#654
b1010111 &
b0000000000011110 (
1-
b0101101 1
#655
0-
#656
b1010110 &
b0000000000011101 (
1-
b1011011 1
#657
0-
#658
b1010101 &
b0000000000011100 (
1-
b0110111 1
#659
0-
#660
b1010100 &
b0000000000011011 (
1-
b1101111 1
#661
0-
#662
b1010011 &
b0000000000011010 (
1-
b1011110 1
#663
0-
#664
b1010010 &
b0000000000011001 (
1-
b0111100 1
#665
0-
#666
b1010001 &
b0000000000011000 (
1-
b1111001 1
#667
0-
#668
b1010000 &
b0000000000010111 (
1-
b1110011 1
#669
0-
#670
b1001111 &
b0000000000010110 (
1-
b1100111 1
#671
0-
#672
b1001110 &
b0000000000010101 (
1-
b1001110 1
#673
0-
#674
b1001101 &
b0000000000010100 (
1-
b0011100 1
#675
0-
#676
b1001100 &
b0000000000010011 (
1-
b0111001 1
#677
0-
#678
b1001011 &
b0000000000010010 (
1-
b1110010 1
#679
0-
#680
b1001010 &
b0000000000010001 (
1-
b1100101 1
#681
0-
#682
b1001001 &
b0000000000010000 (
1-
b1001010 1
#683
0-
#684
b1001000 &
b0000000000001111 (
1-
b0010101 1
#685
0-
#686
b1000111 &
b0000000000001110 (
1-
b0101011 1
#687
0-
#688
b1000110 &
b0000000000001101 (
1-
b1010110 1
#689
0-
#690
b1000101 &
b0000000000001100 (
1-
b0101100 1
#691
0-
